astc_decomp.cpython-39-darwin.so
astc_decomp-1.0.3.dist-info/LICENSE
astc_decomp-1.0.3.dist-info/METADATA
astc_decomp-1.0.3.dist-info/WHEEL
astc_decomp-1.0.3.dist-info/top_level.txt
astc_decomp-1.0.3.dist-info/RECORD
